{
  "name": "Otaku Kingdom",
  "slug": "otaku-kingdom",
  "tagline": "One of the biggest anime community channels we track",
  "description": "Otaku Kingdom is a huge anime community channel — about 68,600 subscribers as of July 2026. It covers anime fandom broadly (Myanmar-based community); like most big anime channels it is not adult-only, but it anchors the anime side of this category.",
  "category": "Hentai & Anime",
  "url": "https://t.me/okmchannnel",
  "pricing": {
    "model": "free"
  },
  "features": [
    "68,000+ subscribers (July 2026)",
    "Massive anime fandom community",
    "Free public channel"
  ],
  "pros": [
    "Largest verified channel in this category",
    "Very active"
  ],
  "cons": [
    "Not NSFW-focused",
    "Regional community (Myanmar)"
  ],
  "rating": 4.3,
  "lastUpdated": "2026-07-09",
  "tags": [
    "hentai-anime",
    "telegram",
    "verified-2026-07"
  ],
  "seoDescription": "One of the biggest anime community channels we track. Verified real and active July 2026 — subscribers, pros & cons and how to join."
}